nauth_sdk/__init__.py
nauth_sdk/settings.py
nauth_sdk-0.0.5.dist-info/METADATA
nauth_sdk-0.0.5.dist-info/RECORD
nauth_sdk-0.0.5.dist-info/WHEEL
nauth_sdk-0.0.5.dist-info/top_level.txt
