Metadata-Version: 2.1
Name: nauth-sdk
Version: 0.0.5
Summary: A simple sdk for nauth
Home-page: UNKNOWN
Author: ntkomata
Author-email: ntkomata@outlook.com
License: UNKNOWN
Platform: UNKNOWN
Classifier: Programming Language :: Python :: 3
Classifier: License :: OSI Approved :: MIT License
Classifier: Operating System :: OS Independent
Requires-Dist: requests
